fortifetch/__init__.py
fortifetch/backend/__init__.py
fortifetch/backend/firewall_db.py
fortifetch/backend/general_db.py
fortifetch/data_cleaning/__init__.py
fortifetch/data_cleaning/network/__init__.py
fortifetch/data_cleaning/network/clean_network_data.py
fortifetch/data_cleaning/policy_object/__init__.py
fortifetch/data_cleaning/policy_object/clean_policy_address.py
fortifetch/data_cleaning/security_profiles/__init__.py
fortifetch/data_cleaning/security_profiles/clean_security_profile.py
fortifetch/data_cleaning/system/__init__.py
fortifetch/data_cleaning/system/clean_device_data.py
fortifetch/data_cleaning/user_authentication/__init__.py
fortifetch/data_cleaning/user_authentication/clean_user_data.py
fortifetch/data_cleaning/vpn/__init__.py
fortifetch/data_cleaning/vpn/clean_vpn_data.py
fortifetch/db/schema.sql
fortifetch/fortifetch/__init__.py
fortifetch/fortifetch/fortifetch.py
fortifetch/main.py
fortifetch/shared/__init__.py
fortifetch/shared/utilities.py
fortifetch/tasks/__init__.py
fortifetch/tasks/fgt_tasks.py
fortifetch-1.0.0.dist-info/LICENSE
fortifetch-1.0.0.dist-info/METADATA
fortifetch-1.0.0.dist-info/WHEEL
fortifetch-1.0.0.dist-info/entry_points.txt
fortifetch-1.0.0.dist-info/RECORD
