Metadata-Version: 2.1
Name: fortifetch
Version: 1.0.0
Summary: FortiFetch is a Python application that gathers information from FortiGate firewalls using the API and saves the information to a SQLite3 database. FortiFetch is built using Typer Python and the rich library for console output, and is designed to be easy to install, configure, and use.
License: MIT
Author: GT
Author-email: geuryt@yahoo.com
Requires-Python: >=3.8,<4.0
Classifier: License :: OSI Approved :: MIT License
Classifier: Programming Language :: Python :: 3
Classifier: Programming Language :: Python :: 3.8
Classifier: Programming Language :: Python :: 3.9
Classifier: Programming Language :: Python :: 3.10
Classifier: Programming Language :: Python :: 3.11
Requires-Dist: fortigate-api (>=1.0.2,<2.0.0)
Requires-Dist: rich (>=13.3.1,<14.0.0)
Requires-Dist: typer[all] (>=0.1.0,<0.2.0)
